oauth/__init__.py
oauth/auth/__init__.py
oauth/auth/application_authentication.py
oauth/models/__init__.py
oauth/models/user.py
oauth/utils/keycloak.py
oauth/views/__init__.py
oauth/views/login_view.py
oauth/views/user_view.py
ssl_oauth-1.0.0.dist-info/METADATA
ssl_oauth-1.0.0.dist-info/WHEEL
ssl_oauth-1.0.0.dist-info/RECORD
