Metadata-Version: 2.1
Name: ssl-oauth
Version: 1.0.0
Summary: #test
Author: Nikita
Author-email: nmamizerov@gmail.ru
Requires-Python: >=3.9,<4.0
Classifier: Programming Language :: Python :: 3
Classifier: Programming Language :: Python :: 3.9
Classifier: Programming Language :: Python :: 3.10
Classifier: Programming Language :: Python :: 3.11
Requires-Dist: django (>=4.2.5,<5.0.0)
Requires-Dist: djangorestframework (>=3.14.0,<4.0.0)
